ipwhois/IPwhois.py
ipwhois/__init__.py
ipwho-0.1.2.dist-info/LICENSE
ipwho-0.1.2.dist-info/METADATA
ipwho-0.1.2.dist-info/WHEEL
ipwho-0.1.2.dist-info/entry_points.txt
ipwho-0.1.2.dist-info/top_level.txt
ipwho-0.1.2.dist-info/RECORD
