Metadata-Version: 2.1
Name: ipwho
Version: 0.1.2
Summary: ip information gathering. originally created by kamabay modified the code to get only some specific data.
Home-page: https://github.com/techdjay/ipwho
Author: Jay
License: Apache License 2.0
Keywords: jay,ipwho,techdjay,ip,whois,information,gathering
Classifier: License :: OSI Approved :: Apache Software License
Classifier: Operating System :: OS Independent
Classifier: Programming Language :: Python :: 3
Classifier: Topic :: Utilities
License-File: LICENSE
Requires-Dist: requests
